qingqiu/__init__.py
qingqiu/check.py
qingqiu/conftest.py
qingqiu/gl.py
qingqiu/handle.py
qingqiu/help.py
qingqiu/qing.py
qingqiu/qiu.py
qingqiu/setup.py
qingqiu/test.py
qingqiu/tools.py
qingqiu/transform.py
qingqiu-0.0.8.dist-info/METADATA
qingqiu-0.0.8.dist-info/WHEEL
qingqiu-0.0.8.dist-info/entry_points.txt
qingqiu-0.0.8.dist-info/top_level.txt
qingqiu-0.0.8.dist-info/RECORD
