Metadata-Version: 2.1
Name: qingqiu
Version: 0.0.8
Summary: 简单得接口测试框架
Home-page: https://gitee.com/tuboyou/qingqiu
Author: lixuecheng
Author-email: lixuechengde@163.com
License: MIT Licence
Keywords: pip,easy,requests,auto
Platform: any
Classifier: Intended Audience :: Developers
Classifier: Topic :: Software Development :: User Interfaces
Classifier: License :: OSI Approved :: MIT License
Classifier: Programming Language :: Python :: 3.5
Classifier: Programming Language :: Python :: 3.6
Classifier: Programming Language :: Python :: 3.7
Classifier: Programming Language :: Python :: 3.8
Classifier: Programming Language :: Python :: 3.9
Classifier: Programming Language :: Python :: 3.10
Classifier: Programming Language :: Python :: 3.11
Requires-Python: >=3.5
Requires-Dist: requests
Requires-Dist: pytest
Requires-Dist: pytest-rerunfailures
Requires-Dist: pytest-html
Requires-Dist: pytest-dependency
Requires-Dist: json-tools
